eas/__init__.py
eas/__main__.py
eas/constants.py
eas/difflist.py
eas/duplicate_list.py
eas/encrypted_storage.py
eas/file_comparator.py
eas/filelist.py
eas/log_receiver.py
eas/path_match.py
eas/pathm.py
eas/scannable.py
eas/staged_task.py
eas/target_runner.py
eas/task.py
eas/authenticator/__init__.py
eas/authenticator/authenticator.py
eas/authenticator/dropbox_authenticator.py
eas/authenticator/exceptions.py
eas/authenticator/generic_authenticator.py
eas/authenticator/yadisk_authenticator.py
eas/cdb/__init__.py
eas/cdb/cdb.py
eas/cdb/logging.py
eas/cli/__init__.py
eas/cli/authenticate_storages.py
eas/cli/common.py
eas/cli/configure.py
eas/cli/decrypt.py
eas/cli/download.py
eas/cli/encrypt.py
eas/cli/environment.py
eas/cli/execute.py
eas/cli/generate_config.py
eas/cli/generate_encrypted_data.py
eas/cli/generic_signal_manager.py
eas/cli/get_key.py
eas/cli/logout.py
eas/cli/pager.py
eas/cli/parse_choice.py
eas/cli/password_prompt.py
eas/cli/prompter.py
eas/cli/remove_duplicates.py
eas/cli/scan.py
eas/cli/set_key.py
eas/cli/set_master_password.py
eas/cli/show_diffs.py
eas/cli/show_duplicates.py
eas/cli/signal_manager.py
eas/cli/sync.py
eas/cli/console/__init__.py
eas/cli/console/console.py
eas/cli/console/console_namespace.py
eas/cli/console/console_program.py
eas/cli/console/commands/__init__.py
eas/cli/console/commands/cat.py
eas/cli/console/commands/cd.py
eas/cli/console/commands/diffs.py
eas/cli/console/commands/download.py
eas/cli/console/commands/duplicates.py
eas/cli/console/commands/echo.py
eas/cli/console/commands/exit.py
eas/cli/console/commands/ls.py
eas/cli/console/commands/remove_duplicates.py
eas/cli/console/commands/scan.py
eas/cli/console/commands/sync.py
eas/common/__init__.py
eas/common/lazy_dict.py
eas/common/lockfile.py
eas/common/lru_cache.py
eas/common/speed_limiter.py
eas/config/__init__.py
eas/config/config.py
eas/config/config_block.py
eas/config/config_namespace.py
eas-0.7.2.dist-info/METADATA
eas-0.7.2.dist-info/RECORD
eas-0.7.2.dist-info/WHEEL
eas-0.7.2.dist-info/entry_points.txt
eas-0.7.2.dist-info/top_level.txt
